MANIFEST.in
plemp.1
setup.py
plemp/__init__.py
plemp/base.py
plemp/flickr.py
plemp/gui.py
plemp/plemp.ui
plemp/progressclient.py
plemp/scripts.py
plemp.egg-info/PKG-INFO
plemp.egg-info/SOURCES.txt
plemp.egg-info/dependency_links.txt
plemp.egg-info/top_level.txt
scripts/plemp