Metadata-Version: 1.0
Name: plemp
Version: 0.4
Summary: Simple commandline flickr upload tool
Home-page: http://scherpenisse.net/plemp
Author: Arjan Scherpenisse
Author-email: arjan@scherpenisse.net
License: MIT/X
Platform: UNKNOWN
Classifier: License :: OSI Approved :: MIT License
Classifier: Programming Language :: Python
Classifier: Topic :: Communications
Classifier: Topic :: Utilities
